odoo/addons/odoo_web_login/README.rst
odoo/addons/odoo_web_login/__init__.py
odoo/addons/odoo_web_login/__manifest__.py
odoo/addons/odoo_web_login/controllers/__init__.py
odoo/addons/odoo_web_login/controllers/main.py
odoo/addons/odoo_web_login/data/ir_config_parameter.xml
odoo/addons/odoo_web_login/static/description/change_background_dawn.jpg
odoo/addons/odoo_web_login/static/description/change_background_day.jpg
odoo/addons/odoo_web_login/static/description/change_background_dusk.jpg
odoo/addons/odoo_web_login/static/description/change_background_night.jpg
odoo/addons/odoo_web_login/static/description/config.jpg
odoo/addons/odoo_web_login/static/description/disable_footer.jpg
odoo/addons/odoo_web_login/static/description/disable_manage_database.jpg
odoo/addons/odoo_web_login/static/description/icon.png
odoo/addons/odoo_web_login/static/src/css/web_login_style.css
odoo/addons/odoo_web_login/static/src/img/background_login_1.png
odoo/addons/odoo_web_login/static/src/img/background_login_2.png
odoo/addons/odoo_web_login/static/src/img/background_login_3.png
odoo/addons/odoo_web_login/static/src/img/background_login_4.png
odoo/addons/odoo_web_login/templates/webclient_templates.xml
odoo/addons/odoo_web_login/templates/website_templates.xml
odoo12_addon_odoo_web_login-12.0.1.0.0.99.dev3.dist-info/METADATA
odoo12_addon_odoo_web_login-12.0.1.0.0.99.dev3.dist-info/WHEEL
odoo12_addon_odoo_web_login-12.0.1.0.0.99.dev3.dist-info/top_level.txt
odoo12_addon_odoo_web_login-12.0.1.0.0.99.dev3.dist-info/RECORD
