Metadata-Version: 2.1
Name: odoo12-addon-odoo-web-login
Version: 12.0.1.0.0.99.dev3
Summary: The new configurable Odoo Web Login Screen
Home-page: http://www.xubi.me
Author: binhnguyenxuan (www.xubi.me)
License: AGPL-3
Platform: UNKNOWN
Classifier: Programming Language :: Python
Classifier: Framework :: Odoo
Classifier: License :: OSI Approved :: GNU Affero General Public License v3
Requires-Python: >=3.5
Requires-Dist: odoo (<12.1dev,>=12.0a)
